{
  "attributes": {
  },
  "suggestions": {
  },
  "version": "0.0.1",
  "long_description": "Description\n===========\n\nRequirements\n============\n\nAttributes\n==========\n\nUsage\n=====\n\n",
  "description": "Installs/Configures splunk",
  "recipes": {
    "splunk::install": "Installs splunk from a tar a file. Uses attributes and definitions"
  },
  "dependencies": {
    "rightscale": ">= 0.0.0"
  },
  "maintainer_email": "YOUR_EMAIL",
  "recommendations": {
  },
  "license": "All rights reserved",
  "replacing": {
  },
  "maintainer": "YOUR_COMPANY_NAME",
  "name": "splunk",
  "groupings": {
  },
  "providing": {
  },
  "conflicting": {
  },
  "platforms": {
  }
}